{"guid":"root________","title":"","index":0,"dateAdded":1563441097724000,"lastModified":1563877147722000,"id":1,"typeCode":2,"type":"text/x-moz-place-container","root":"placesRoot","children":[{"guid":"menu________","title":"menu","index":0,"dateAdded":1563441097724000,"lastModified":1563441098701000,"id":2,"typeCode":2,"type":"text/x-moz-place-container","root":"bookmarksMenuFolder","children":[{"guid":"4xIlJSMaSDRl","title":"Mozilla Firefox","index":0,"dateAdded":1563441098701000,"lastModified":1563441098701000,"id":7,"typeCode":2,"type":"text/x-moz-place-container","children":[{"guid":"hjR6GVUe3Ak9","title":"Help and Tutorials","index":0,"dateAdded":1563441098701000,"lastModified":1563441098701000,"id":8,"typeCode":1,"iconuri":"fake-favicon-uri:https://support.mozilla.org/en-US/products/firefox","type":"text/x-moz-place","uri":"https://support.mozilla.org/en-US/products/firefox"},{"guid":"VcspqPEdQBpl","title":"Customize Firefox","index":1,"dateAdded":1563441098701000,"lastModified":1563441098701000,"id":9,"typeCode":1,"iconuri":"fake-favicon-uri:https://support.mozilla.org/en-US/kb/customize-firefox-controls-buttons-and-toolbars?utm_source=firefox-browser&utm_medium=default-bookmarks&utm_campaign=customize","type":"text/x-moz-place","uri":"https://support.mozilla.org/en-US/kb/customize-firefox-controls-buttons-and-toolbars?utm_source=firefox-browser&utm_medium=default-bookmarks&utm_campaign=customize"},{"guid":"fRMftxvYcv2u","title":"Get Involved","index":2,"dateAdded":1563441098701000,"lastModified":1563441098701000,"id":10,"typeCode":1,"iconuri":"fake-favicon-uri:https://www.mozilla.org/en-US/contribute/","type":"text/x-moz-place","uri":"https://www.mozilla.org/en-US/contribute/"},{"guid":"1FmHqRQ6AX6G","title":"About Us","index":3,"dateAdded":1563441098701000,"lastModified":1563441098701000,"id":11,"typeCode":1,"iconuri":"fake-favicon-uri:https://www.mozilla.org/en-US/about/","type":"text/x-moz-place","uri":"https://www.mozilla.org/en-US/about/"}]},{"guid":"vHDN3QD_gmrj","title":"Ubuntu and Free Software links","index":1,"dateAdded":1563441098701000,"lastModified":1563441098701000,"id":12,"typeCode":2,"type":"text/x-moz-place-container","children":[{"guid":"1A8tLFaaRHQh","title":"Ubuntu","index":0,"dateAdded":1563441098701000,"lastModified":1563441098701000,"id":13,"typeCode":1,"iconuri":"fake-favicon-uri:http://www.ubuntu.com/","type":"text/x-moz-place","uri":"http://www.ubuntu.com/"},{"guid":"u8sBcxzjoorq","title":"Ubuntu Wiki (community-edited website)","index":1,"dateAdded":1563441098701000,"lastModified":1563441098701000,"id":14,"typeCode":1,"iconuri":"fake-favicon-uri:http://wiki.ubuntu.com/","type":"text/x-moz-place","uri":"http://wiki.ubuntu.com/"},{"guid":"h9Wism2OEULP","title":"Make a Support Request to the Ubuntu Community","index":2,"dateAdded":1563441098701000,"lastModified":1563441098701000,"id":15,"typeCode":1,"iconuri":"fake-favicon-uri:https://answers.launchpad.net/ubuntu/+addquestion","type":"text/x-moz-place","uri":"https://answers.launchpad.net/ubuntu/+addquestion"},{"guid":"4dzwr3tf3vTw","title":"Debian (Ubuntu is based on Debian)","index":3,"dateAdded":1563441098701000,"lastModified":1563441098701000,"id":16,"typeCode":1,"iconuri":"fake-favicon-uri:http://www.debian.org/","type":"text/x-moz-place","uri":"http://www.debian.org/"}]}]},{"guid":"toolbar_____","title":"toolbar","index":1,"dateAdded":1563441097724000,"lastModified":1563877147722000,"id":3,"typeCode":2,"type":"text/x-moz-place-container","root":"toolbarFolder","children":[{"guid":"sxq2oczzk13d","title":"fcswlva1","index":0,"dateAdded":1563441140484000,"lastModified":1563446134884000,"id":18,"typeCode":1,"type":"text/x-moz-place","uri":"http://fcswlva1.za.pkb.sk/switchExplorer_installed.html"},{"guid":"sWsdiYwb36nU","title":"fcswlva3","index":1,"dateAdded":1563441201316000,"lastModified":1563441211984000,"id":19,"typeCode":1,"type":"text/x-moz-place","uri":"http://fcswlva3.za.pkb.sk/switchExplorer_installed.html"},{"guid":"sXIzDSvVMuON","title":"fcswlva4bc3","index":2,"dateAdded":1563446150494000,"lastModified":1563446249493000,"id":20,"typeCode":1,"type":"text/x-moz-place","uri":"http://fcswlva4bc3.dmz.pkb.sk/switchExplorer_installed.html"},{"guid":"QHVp_HCh7Uy2","title":"fcswlva5bc7","index":3,"dateAdded":1563446319017000,"lastModified":1563446496179000,"id":21,"typeCode":1,"type":"text/x-moz-place","uri":"http://fcswlva5bc7.za.pkb.sk/switchExplorer_installed.html"},{"guid":"-rdyRWr-yWHh","title":"fcswlvb1","index":4,"dateAdded":1563446565093000,"lastModified":1563446599701000,"id":22,"typeCode":1,"type":"text/x-moz-place","uri":"http://fcswlvb1.za.pkb.sk/switchExplorer_installed.html"},{"guid":"S-y6AZocN_jk","title":"fcswlvb3","index":5,"dateAdded":1563446615914000,"lastModified":1563446631044000,"id":23,"typeCode":1,"type":"text/x-moz-place","uri":"http://fcswlvb3.za.pkb.sk/switchExplorer_installed.html"},{"guid":"WKEQmGoHQWpR","title":"fcswlvb4bc3","index":6,"dateAdded":1563446648615000,"lastModified":1563446668174000,"id":24,"typeCode":1,"type":"text/x-moz-place","uri":"http://fcswlvb4bc3.dmz.pkb.sk/switchExplorer_installed.html"},{"guid":"UiUvnYo_KZWK","title":"fcswlvb5bc7","index":7,"dateAdded":1563446687011000,"lastModified":1563446703042000,"id":25,"typeCode":1,"type":"text/x-moz-place","uri":"http://fcswlvb5bc7.za.pkb.sk/switchExplorer_installed.html"},{"guid":"T4bLSEYi5Nkq","title":"","index":8,"dateAdded":1563877140294000,"lastModified":1563877147722000,"id":34,"typeCode":3,"type":"text/x-moz-place-separator"},{"guid":"YCEe-oWmkvXZ","title":"fcswbka1","index":9,"dateAdded":1563446742816000,"lastModified":1563446762327000,"id":26,"typeCode":1,"type":"text/x-moz-place","uri":"http://fcswbka1.za.pkb.sk/switchExplorer_installed.html"},{"guid":"w2AmkSWmTPgA","title":"fcswbka3","index":10,"dateAdded":1563446836717000,"lastModified":1563446849035000,"id":27,"typeCode":1,"type":"text/x-moz-place","uri":"http://fcswbka3.za.pkb.sk/switchExplorer_installed.html"},{"guid":"rTN5AxIdPqnM","title":"fcswbka4bc4","index":11,"dateAdded":1563446882135000,"lastModified":1563446967424000,"id":28,"typeCode":1,"type":"text/x-moz-place","uri":"http://fcswbka4bc4.dmz.pkb.sk/switchExplorer_installed.html"},{"guid":"2lhSZoweYiCm","title":"fcswbka5bc8","index":12,"dateAdded":1563446984674000,"lastModified":1563447013090000,"id":29,"typeCode":1,"type":"text/x-moz-place","uri":"http://fcswbka5bc8.za.pkb.sk/switchExplorer_installed.html"},{"guid":"elzBWycfqQmg","title":"fcswbkb1","index":13,"dateAdded":1563447766723000,"lastModified":1563447779080000,"id":30,"typeCode":1,"type":"text/x-moz-place","uri":"http://fcswbkb1.za.pkb.sk/switchExplorer_installed.html"},{"guid":"LOc5c5TqkVDM","title":"fcswbkb3","index":14,"dateAdded":1563447801611000,"lastModified":1563447821856000,"id":31,"typeCode":1,"type":"text/x-moz-place","uri":"http://fcswbkb3.za.pkb.sk/switchExplorer_installed.html"},{"guid":"Drh0dkPgKCaH","title":"fcswbkb4bc4","index":15,"dateAdded":1563447866064000,"lastModified":1563447879477000,"id":32,"typeCode":1,"type":"text/x-moz-place","uri":"http://fcswbkb4bc4.dmz.pkb.sk/switchExplorer_installed.html"},{"guid":"kNsqNnNN8ccp","title":"fcswbkb5bc8","index":16,"dateAdded":1563447901360000,"lastModified":1563447914420000,"id":33,"typeCode":1,"type":"text/x-moz-place","uri":"http://fcswbkb5bc8.za.pkb.sk/switchExplorer_installed.html"}]},{"guid":"unfiled_____","title":"unfiled","index":3,"dateAdded":1563441097724000,"lastModified":1563441190138000,"id":5,"typeCode":2,"type":"text/x-moz-place-container","root":"unfiledBookmarksFolder"},{"guid":"mobile______","title":"mobile","index":4,"dateAdded":1563441097746000,"lastModified":1563441098693000,"id":6,"typeCode":2,"type":"text/x-moz-place-container","root":"mobileFolder"}]}